anaplan_api/__init__.py
anaplan_api/anaplan/__init__.py
anaplan_api/anaplan/Action.py
anaplan_api/anaplan/ActionParser.py
anaplan_api/anaplan/ActionTask.py
anaplan_api/anaplan/anaplan.py
anaplan_api/anaplan/authentication/__init__.py
anaplan_api/anaplan/authentication/AnaplanAuthentication.py
anaplan_api/anaplan/authentication/AuthenticationFactory.py
anaplan_api/anaplan/authentication/AuthorizationManager.py
anaplan_api/anaplan/authentication/BasicAuthentication.py
anaplan_api/anaplan/authentication/CertificateAuthentication.py
anaplan_api/anaplan/authentication/CertificateHandler.py
anaplan_api/anaplan/bases/__init__.py
anaplan_api/anaplan/bases/AnaplanResource.py
anaplan_api/anaplan/bases/ResourceParserFactory.py
anaplan_api/anaplan/bases/TaskFactory.py
anaplan_api/anaplan/ExportParser.py
anaplan_api/anaplan/ExportTask.py
anaplan_api/anaplan/File.py
anaplan_api/anaplan/FileDownload.py
anaplan_api/anaplan/FileUpload.py
anaplan_api/anaplan/ImportParser.py
anaplan_api/anaplan/ImportTask.py
anaplan_api/anaplan/KeystoreManager.py
anaplan_api/anaplan/Model.py
anaplan_api/anaplan/models/__init__.py
anaplan_api/anaplan/models/ActionResponse.py
anaplan_api/anaplan/models/AnaplanConnection.py
anaplan_api/anaplan/models/AnaplanResourceFile.py
anaplan_api/anaplan/models/AnaplanResourceList.py
anaplan_api/anaplan/models/AnaplanVersion.py
anaplan_api/anaplan/models/AuthToken.py
anaplan_api/anaplan/models/ModelDetails.py
anaplan_api/anaplan/models/ParserResponse.py
anaplan_api/anaplan/models/TaskResponse.py
anaplan_api/anaplan/models/UserDetails.py
anaplan_api/anaplan/models/WorkspaceDetails.py
anaplan_api/anaplan/ParameterAction.py
anaplan_api/anaplan/Parser.py
anaplan_api/anaplan/ProcessParser.py
anaplan_api/anaplan/ProcessTask.py
anaplan_api/anaplan/pyjks/__init__.py
anaplan_api/anaplan/pyjks/jks/__init__.py
anaplan_api/anaplan/pyjks/jks/jks.py
anaplan_api/anaplan/pyjks/jks/rfc2898.py
anaplan_api/anaplan/pyjks/jks/sun_crypto.py
anaplan_api/anaplan/pyjks/jks/util.py
anaplan_api-0.3.4.dist-info/LICENSE
anaplan_api-0.3.4.dist-info/METADATA
anaplan_api-0.3.4.dist-info/WHEEL
anaplan_api-0.3.4.dist-info/RECORD
