Metadata-Version: 2.1
Name: anaplan-api
Version: 0.3.4
Summary: A Python wrapper for the Anaplan Bulk API
Author: Jesse Wilson
Author-email: jeswils@gmail.com
Requires-Python: >=3.9,<4.0
Classifier: Programming Language :: Python :: 3
Classifier: Programming Language :: Python :: 3.9
Classifier: Programming Language :: Python :: 3.10
Classifier: Programming Language :: Python :: 3.11
Classifier: Programming Language :: Python :: 3.12
Requires-Dist: certifi (>=2024.7.4,<2025.0.0)
Requires-Dist: cryptography (>=42.0.8,<43.0.0)
Requires-Dist: idna (>=3.7,<4.0)
Requires-Dist: javaobj-py3 (>=0.4.3,<0.5.0)
Requires-Dist: pandas (>=2.2.1,<3.0.0)
Requires-Dist: pyasn1 (>=0.6.0,<0.7.0)
Requires-Dist: pyasn1-modules (>=0.4.0,<0.5.0)
Requires-Dist: requests (>=2.32.3,<3.0.0)
Requires-Dist: urllib3 (>=2.2.2,<3.0.0)
